bribrain/__init__.py
bribrain/bridrive.py
bribrain/config.py
bribrain/function.py
bribrain/ingestion.py
bribrain/load.py
bribrain/seaf-share.py
bribrain-1.2.0.dist-info/METADATA
bribrain-1.2.0.dist-info/WHEEL
bribrain-1.2.0.dist-info/top_level.txt
bribrain-1.2.0.dist-info/RECORD
