Metadata-Version: 2.1
Name: bribrain
Version: 1.2.0
Summary: BRIBrain Standardization Code
Home-page: UNKNOWN
Author: Andri Ariyanto
Author-email: ariyant.andri@gmail.com
License: UNKNOWN
Keywords: bribrain,dbb,ddb,python,gondrol,andri ariyanto
Platform: UNKNOWN
Classifier: Programming Language :: Python :: 3
Classifier: Operating System :: Unix
Classifier: Operating System :: MacOS :: MacOS X
Classifier: Operating System :: Microsoft :: Windows
Requires-Dist: mysql-connector-python ==8.0.28
Requires-Dist: psycopg2
